Workbook
Name rendimento_carteira: Planilha1!$D$7

Sheet Planilha1
B5: Configurações
B6: Salário | D6: 4200
B7: Rendimento Carteira | D7: 0.006
B8: Sugestão Investimento | D8: =D6*0.3 -> 1260
B10: Investimento Mensal
B11: Quanto Investir? | D11: =D8 -> 1260
B12: Por quantos anos? | D12: 10
B13: Taxa de Rendimento Mensal? | D13: 0.01079
B14: Patrimônio acumulado? | D14: =FV(D13,D12*12,-D11,,0) -> 306538.11
B15: Dividendos mensais? | D15: =D14*$D$7 -> 1839.2286
B17: Cenários | C17: Patrimônio | D17: Dividendos
A18: 2 | B18: Quanto em 2 anos? | C18: =FV($D$13,A18*12,-$D$11) -> 34306.81 | D18: =C18*$D$7 -> 205.84086
A19: 5 | B19: Quanto em 5 anos? | C19: =FV($D$13,A19*12,-$D$11) -> 105558.91 | D19: =C19*$D$7 -> 633.35347
A20: 10 | B20: Quanto em 10 anos? | C20: =FV($D$13,A20*12,-$D$11) -> 306538.11 | D20: =C20*$D$7 -> 1839.2286
A21: 20 | B21: Quanto em 20 anos? | C21: =FV($D$13,A21*12,-$D$11) -> 1417750 | D21: =C21*$D$7 -> 8506.4999
A22: 30 | B22: Quanto em 30 anos? | C22: =FV($D$13,A22*12,-$D$11) -> 5445933.8 | D22: =C22*$D$7 -> 32675.603
B24: Perfil | D24: Conservador
B25: VALOR A SER INVESTIDO POR MÊS | D25: =D8 -> 1260
B27: TIPO DE FII | C27: Percentual Sugerido | D27: Valores
B28: PAPEL | C28: =VLOOKUP($D$24&B28,Planilha2!$A$3:$D$20,4,0) -> 0.3 | D28: =$D$25*C28 -> 378
B29: TIJOLO | C29: =VLOOKUP($D$24&B29,Planilha2!$A$3:$D$20,4,0) -> 0.5 | D29: =$D$25*C29 -> 630
B30: HÍBRIDOS | C30: =VLOOKUP($D$24&B30,Planilha2!$A$3:$D$20,4,0) -> 0.1 | D30: =$D$25*C30 -> 126
B31: FOFs | C31: =VLOOKUP($D$24&B31,Planilha2!$A$3:$D$20,4,0) -> 0.1 | D31: =$D$25*C31 -> 126
B32: DESENVOLVIMENTO | C32: =VLOOKUP($D$24&B32,Planilha2!$A$3:$D$20,4,0) -> 0 | D32: =$D$25*C32 -> 0
B33: HOTELARIAS | C33: =VLOOKUP($D$24&B33,Planilha2!$A$3:$D$20,4,0) -> 0 | D33: =$D$25*C33 -> 0
B34: TOTAL | C34: =SUM(C28:C33) -> 1 | D34: =SUM(D28:D33) -> 1260

Sheet Planilha2
A2: CHAVE | B2: PERFIL | C2: TIPO DE FII | D2: %
A3: =B3&C3 -> ConservadorPAPEL | B3: Conservador | C3: PAPEL | D3: 0.3 | E3: =SUM(D3:D8) -> 1
A4: =B4&C4 -> ConservadorTIJOLO | B4: Conservador | C4: TIJOLO | D4: 0.5
A5: =B5&C5 -> ConservadorHÍBRIDOS | B5: Conservador | C5: HÍBRIDOS | D5: 0.1
A6: =B6&C6 -> ConservadorFOFs | B6: Conservador | C6: FOFs | D6: 0.1
A7: =B7&C7 -> ConservadorDESENVOLVIMENTO | B7: Conservador | C7: DESENVOLVIMENTO | D7: 0
A8: =B8&C8 -> ConservadorHOTELARIAS | B8: Conservador | C8: HOTELARIAS | D8: 0
A9: =B9&C9 -> ModeradoPAPEL | B9: Moderado | C9: PAPEL | D9: 0.32 | E9: =SUM(D9:D14) -> 1
A10: =B10&C10 -> ModeradoTIJOLO | B10: Moderado | C10: TIJOLO | D10: 0.4
A11: =B11&C11 -> ModeradoHÍBRIDOS | B11: Moderado | C11: HÍBRIDOS | D11: 0.08
A12: =B12&C12 -> ModeradoFOFs | B12: Moderado | C12: FOFs | D12: 0.1
A13: =B13&C13 -> ModeradoDESENVOLVIMENTO | B13: Moderado | C13: DESENVOLVIMENTO | D13: 0.1
A14: =B14&C14 -> ModeradoHOTELARIAS | B14: Moderado | C14: HOTELARIAS | D14: 0
A15: =B15&C15 -> AgressivoPAPEL | B15: Agressivo | C15: PAPEL | D15: 0.5 | E15: =SUM(D15:D20) -> 1
A16: =B16&C16 -> AgressivoTIJOLO | B16: Agressivo | C16: TIJOLO | D16: 0.1
A17: =B17&C17 -> AgressivoHÍBRIDOS | B17: Agressivo | C17: HÍBRIDOS | D17: 0.05
A18: =B18&C18 -> AgressivoFOFs | B18: Agressivo | C18: FOFs | D18: 0.05
A19: =B19&C19 -> AgressivoDESENVOLVIMENTO | B19: Agressivo | C19: DESENVOLVIMENTO | D19: 0.2
A20: =B20&C20 -> AgressivoHOTELARIAS | B20: Agressivo | C20: HOTELARIAS | D20: 0.1
